basecrm/__init__.py
basecrm/client.py
basecrm/coercion.py
basecrm/configuration.py
basecrm/errors.py
basecrm/http_client.py
basecrm/services.py
basecrm/sync.py
basecrm/version.py
basecrm/test/__init__.py
basecrm/test/test_accounts_service.py
basecrm/test/test_associated_contacts_service.py
basecrm/test/test_coercion.py
basecrm/test/test_contacts_service.py
basecrm/test/test_deal_sources_service.py
basecrm/test/test_deal_unqualified_reasons_service.py
basecrm/test/test_deals_service.py
basecrm/test/test_http_client.py
basecrm/test/test_lead_sources_service.py
basecrm/test/test_lead_unqualified_reasons_service.py
basecrm/test/test_leads_service.py
basecrm/test/test_line_items_service.py
basecrm/test/test_loss_reasons_service.py
basecrm/test/test_notes_service.py
basecrm/test/test_orders_service.py
basecrm/test/test_pipelines_service.py
basecrm/test/test_products_service.py
basecrm/test/test_sources_service.py
basecrm/test/test_stages_service.py
basecrm/test/test_sync.py
basecrm/test/test_sync_service.py
basecrm/test/test_tags_service.py
basecrm/test/test_tasks_service.py
basecrm/test/test_text_messages_service.py
basecrm/test/test_users_service.py
basecrm/test/test_visit_outcomes_service.py
basecrm/test/test_visits_service.py
basecrm/test/testutils.py
basecrm-1.2.9.dist-info/LICENSE
basecrm-1.2.9.dist-info/METADATA
basecrm-1.2.9.dist-info/WHEEL
basecrm-1.2.9.dist-info/top_level.txt
basecrm-1.2.9.dist-info/RECORD
